Metadata-Version: 2.1
Name: FairQt
Version: 2.1.0
Summary: pyQt6 plus Qt Designer Support Framework
Home-page: https://github.com/chazzcoin/FairQt
Author: ChazzCoin
Author-email: chazzcoin@gmail.com
License: BSD 2-clause
Platform: UNKNOWN
Classifier: Development Status :: 1 - Planning
Classifier: Intended Audience :: Science/Research
Classifier: License :: OSI Approved :: BSD License
Classifier: Operating System :: POSIX :: Linux
Classifier: Programming Language :: Python :: 3.8
Classifier: Programming Language :: Python :: 3.9
